NSO1212v1/__init__.py
NSO1212v1/module.py
nso1212v1-1.0.0.dist-info/licenses/LICENSE
nso1212v1-1.0.0.dist-info/METADATA
nso1212v1-1.0.0.dist-info/WHEEL
nso1212v1-1.0.0.dist-info/top_level.txt
nso1212v1-1.0.0.dist-info/RECORD
