Metadata-Version: 2.4
Name: NSO1212v1
Version: 1.0.0
Summary: National Statistical Office of Mongolia's Open Data API v1 Handler for Python
Author-email: Makhgal Ganbold <makhgal@num.edu.mn>
License: MIT License
Requires-Python: >=3.12
License-File: LICENSE
Requires-Dist: pandas
Requires-Dist: requests
Dynamic: license-file
